vak/__about__.py
vak/__init__.py
vak/__main__.py
vak/cli/__init__.py
vak/cli/cli.py
vak/cli/eval.py
vak/cli/learncurve.py
vak/cli/predict.py
vak/cli/prep.py
vak/cli/train.py
vak/common/__init__.py
vak/common/accelerator.py
vak/common/annotation.py
vak/common/constants.py
vak/common/converters.py
vak/common/labels.py
vak/common/learncurve.py
vak/common/logging.py
vak/common/paths.py
vak/common/tensorboard.py
vak/common/timebins.py
vak/common/timenow.py
vak/common/typing.py
vak/common/validators.py
vak/common/files/__init__.py
vak/common/files/files.py
vak/common/files/spect.py
vak/config/__init__.py
vak/config/config.py
vak/config/dataset.py
vak/config/eval.py
vak/config/learncurve.py
vak/config/load.py
vak/config/model.py
vak/config/predict.py
vak/config/prep.py
vak/config/spect_params.py
vak/config/train.py
vak/config/trainer.py
vak/config/valid-version-1.2.toml
vak/config/validators.py
vak/datapipes/__init__.py
vak/datapipes/frame_classification/__init__.py
vak/datapipes/frame_classification/constants.py
vak/datapipes/frame_classification/helper.py
vak/datapipes/frame_classification/infer_datapipe.py
vak/datapipes/frame_classification/metadata.py
vak/datapipes/frame_classification/train_datapipe.py
vak/datapipes/parametric_umap/__init__.py
vak/datapipes/parametric_umap/metadata.py
vak/datapipes/parametric_umap/parametric_umap.py
vak/datasets/__init__.py
vak/datasets/cmacbench.py
vak/datasets/get.py
vak/eval/__init__.py
vak/eval/eval_.py
vak/eval/frame_classification.py
vak/eval/parametric_umap.py
vak/learncurve/__init__.py
vak/learncurve/curvefit.py
vak/learncurve/dirname.py
vak/learncurve/frame_classification.py
vak/learncurve/learncurve.py
vak/metrics/__init__.py
vak/metrics/util.py
vak/metrics/classification/__init__.py
vak/metrics/classification/classification.py
vak/metrics/classification/functional.py
vak/metrics/distance/__init__.py
vak/metrics/distance/distance.py
vak/metrics/distance/functional.py
vak/models/__init__.py
vak/models/convencoder_umap.py
vak-1.0.5.dist-info/entry_points.txt
vak-1.0.5.dist-info/licenses/LICENSE
vak-1.0.5.dist-info/WHEEL
vak-1.0.5.dist-info/METADATA
vak-1.0.5.dist-info/RECORD
