Metadata-Version: 2.4
Name: vak
Version: 1.0.5
Summary: A neural network framework for researchers studying acoustic communication
Author-email: David Nicholson <nickledave@users.noreply.github.com>
Requires-Python: >=3.12
Classifier: License :: OSI Approved :: BSD License
Classifier: Development Status :: 5 - Production/Stable
Classifier: Programming Language :: Python
Classifier: Programming Language :: Python :: 3
Classifier: Programming Language :: Python :: 3.12
Classifier: Programming Language :: Python :: 3.13
Classifier: Programming Language :: Python :: 3.14
Classifier: Programming Language :: Python :: Implementation :: CPython
License-File: LICENSE
Requires-Dist: attrs >=25.3.0
Requires-Dist: crowsetta >=5.1.3
Requires-Dist: dask[dataframe] >=2025.5.1
Requires-Dist: evfuncs >=0.3.4
Requires-Dist: joblib >=1.5.1
Requires-Dist: lightning >=2.2.4
Requires-Dist: matplotlib >=3.9.0
Requires-Dist: numpy >=2.0.0
Requires-Dist: pynndescent >=0.5.13
Requires-Dist: scipy >=1.12.0
Requires-Dist: SoundFile >=0.13.1
Requires-Dist: pandas >=2.2.0
Requires-Dist: tensorboard >=2.8.0
Requires-Dist: tomlkit >=0.12.4
Requires-Dist: torch >= 2.7.0
Requires-Dist: torchvision >=0.22.0
Requires-Dist: tqdm >=4.67.1
Requires-Dist: umap-learn >=0.5.9
Project-URL: Documentation, https://vak.readthedocs.io
Project-URL: Source, https://github.com/vocalpy/vak
